primaschema/__init__.py
primaschema/cli.py
primaschema/lib.py
primaschema/data/__init__.py
primaschema-0.2.0.dist-info/LICENSE
primaschema-0.2.0.dist-info/METADATA
primaschema-0.2.0.dist-info/WHEEL
primaschema-0.2.0.dist-info/entry_points.txt
primaschema-0.2.0.dist-info/top_level.txt
primaschema-0.2.0.dist-info/RECORD
