Metadata-Version: 2.1
Name: primaschema
Version: 0.2.0
Summary: A toolkit for primer scheme defintions
License: MIT License
Keywords: genomics
Classifier: Framework :: Django
Classifier: Programming Language :: Python :: 3.10
Classifier: Environment :: Console
Classifier: Intended Audience :: Science/Research
Classifier: License :: OSI Approved :: MIT License
Classifier: Natural Language :: English
Classifier: Operating System :: POSIX :: Linux
Classifier: Operating System :: MacOS
Requires-Python: >=3.10
License-File: LICENSE
Requires-Dist: biopython (==1.80)
Requires-Dist: defopt (==6.4.0)
Requires-Dist: pandas (>=1.5.3)
Requires-Dist: pre-commit
Requires-Dist: pytest
Requires-Dist: jsonschema
Requires-Dist: pyyaml
